LICENSE
MANIFEST.in
README.md
setup.py
ZhongLP/__init__.py
ZhongLP/converter.py
ZhongLP/segmenter.py
ZhongLP/utils_zh.py
ZhongLP.egg-info/PKG-INFO
ZhongLP.egg-info/SOURCES.txt
ZhongLP.egg-info/dependency_links.txt
ZhongLP.egg-info/top_level.txt
ZhongLP/converter_pk/__init__.py
ZhongLP/converter_pk/langconv.py
ZhongLP/converter_pk/zh_wiki.py
ZhongLP/segmenter_pk/__init__.py
ZhongLP/segmenter_pk/shortest_bigram.py
ZhongLP/zzz_data/__init__.py
ZhongLP/zzz_data/bigram_freq.py
ZhongLP/zzz_data/token_index.py
demo/try_converter.py
demo/try_ngram_shortest.py
demo/try_ngram_shortest_bak.py
demo/try_segmenter.py
demo/try_shortest_bigram.py
demo/try_utils.py