Metadata-Version: 2.1
Name: ZhongLP
Version: 0.0.4
Summary: A Zhongwen (Chinese) Language Processing Package.
Home-page: https://github.com/Li-Ming-Fan/ZhongLP
Author: Ming-Fan Li
Author-email: li_m_f@163.com
Maintainer: Ming-Fan Li
Maintainer-email: li_m_f@163.com
License: UNKNOWN
Platform: any
